easyadmin/__init__.py
easyadmin/elements/__init__.py
easyadmin/elements/buttons.py
easyadmin/elements/card.py
easyadmin/elements/forms.py
easyadmin/elements/html_input.py
easyadmin/elements/modal.py
easyadmin/elements/row.py
easyadmin/elements/scripts.py
easyadmin/elements/sidebar.py
easyadmin/elements/table.py
easyadmin/pages/__init__.py
easyadmin/pages/admin.py
easyadmin/pages/admin_table.py
easyadmin/pages/errors.py
easyadmin/pages/login.py
easyadmin/pages/register.py
easyadmin-0.169.dist-info/LICENSE
easyadmin-0.169.dist-info/METADATA
easyadmin-0.169.dist-info/WHEEL
easyadmin-0.169.dist-info/top_level.txt
easyadmin-0.169.dist-info/RECORD
