Metadata-Version: 2.1
Name: easyadmin
Version: 0.169
Summary: Generate pre-formatted HTML elements for an Admin type front-end
Home-page: https://github.com/codemation/easyadmin
Author: Joshua Jamison
Author-email: joshjamison1@gmail.com
License: UNKNOWN
Platform: UNKNOWN
Classifier: Programming Language :: Python :: 3
Classifier: License :: OSI Approved :: MIT License
Classifier: Operating System :: OS Independent
Requires-Python: >=3.7, <4
